cubone/__init__.py
cubone/cli/__init__.py
cubone/cli/core.py
cubone/functions.py
cubone/modules/__init__.py
cubone/modules/network/__init__.py
cubone/questions.py
cubone/settings.py
cubone/tests/__init__.py
cubone-0.1.2.dist-info/entry_points.txt
cubone-0.1.2.dist-info/LICENSE
cubone-0.1.2.dist-info/WHEEL
cubone-0.1.2.dist-info/METADATA
cubone-0.1.2.dist-info/RECORD
