Metadata-Version: 2.1
Name: cubone
Version: 0.1.2
Summary: A pygame scaffold package
License: MIT
Author: Francisco
Author-email: vieirafrancisco.dev@gmail.com
Requires-Python: >=3.8,<4.0
Classifier: License :: OSI Approved :: MIT License
Classifier: Programming Language :: Python :: 3
Classifier: Programming Language :: Python :: 3.10
Classifier: Programming Language :: Python :: 3.8
Classifier: Programming Language :: Python :: 3.9
Requires-Dist: Jinja2 (>=3.1.2,<4.0.0)
Requires-Dist: click (>=8.1.3,<9.0.0)
Requires-Dist: pygame (>=2.1.2,<3.0.0)
